uzbek_lemmatization/__init__.py
uzbek_lemmatization/uzbek_lemmatization.py
uzbek_lemmatization/suzlar/istisnolar.txt
uzbek_lemmatization/suzlar/kfsq.txt
uzbek_lemmatization/suzlar/mustaqil__fel.txt
uzbek_lemmatization/suzlar/mustaqil__olmosh.txt
uzbek_lemmatization/suzlar/mustaqil__ot.txt
uzbek_lemmatization/suzlar/mustaqil__ravish.txt
uzbek_lemmatization/suzlar/mustaqil__sifat.txt
uzbek_lemmatization/suzlar/mustaqil__son.txt
uzbek_lemmatization/suzlar/oraliq__modal.txt
uzbek_lemmatization/suzlar/oraliq__taqlid.txt
uzbek_lemmatization/suzlar/oraliq__undov.txt
uzbek_lemmatization/suzlar/qoshma__fel.txt
uzbek_lemmatization/suzlar/qoshma__olmosh.txt
uzbek_lemmatization/suzlar/qoshma__ravish.txt
uzbek_lemmatization/suzlar/qoshma__undov.txt
uzbek_lemmatization/suzlar/yordamchi__boglovchi.txt
uzbek_lemmatization/suzlar/yordamchi__komakchi.txt
uzbek_lemmatization/suzlar/yordamchi__yuklama.txt
uzbek_lemmatization-2.dist-info/METADATA
uzbek_lemmatization-2.dist-info/WHEEL
uzbek_lemmatization-2.dist-info/top_level.txt
uzbek_lemmatization-2.dist-info/RECORD
